gooder_cv/__init__.py
gooder_cv-1.2.1.dist-info/LICENSE
gooder_cv-1.2.1.dist-info/METADATA
gooder_cv-1.2.1.dist-info/WHEEL
gooder_cv-1.2.1.dist-info/top_level.txt
gooder_cv-1.2.1.dist-info/RECORD
