Metadata-Version: 2.1
Name: gooder-cv
Version: 1.2.1
Author: haogooder
License: MIT
Classifier: Programming Language :: Python
Classifier: License :: OSI Approved :: MIT License
Classifier: Operating System :: OS Independent
Requires-Python: >=3.6
License-File: LICENSE
Requires-Dist: opencv-contrib-python (~=4.6.0.66)
Requires-Dist: opencv-python (~=4.6.0.66)
Requires-Dist: numpy (~=1.23.4)
